{
  "project_info": {
    "project_number": "1001481265213",
    "project_id": "cuceiia-78e62",
    "storage_bucket": "cuceiia-78e62.firebasestorage.app"
  },
  "client": [
    {
      "client_info": {
        "mobilesdk_app_id": "1:1001481265213:android:33720679bfb86c1b164a54",
        "android_client_info": {
          "package_name": "com.example.cuceiai"
        }
      },
      "oauth_client": [],
      "api_key": [
        {
          "current_key": "AIzaSyAMkIaihKcHm0-FPf6RtCz6Ymy8pxqPC0c"
        }
      ],
      "services": {
        "appinvite_service": {
          "other_platform_oauth_client": []
        }
      }
    }
  ],
  "configuration_version": "1"
}